homebrew/settingstrojan/settingstrojan.bin
naomi/README.md
naomi/__init__.py
naomi/eeprom.py
naomi/generic_patch.py
naomi/py.typed
naomi/rom.py
naomi/rom_patch.py
naomi/settings/README.md
naomi/settings/__init__.py
naomi/settings/editor.py
naomi/settings/py.typed
naomi/settings/settings.py
naomi/settings/definitions/BAC0.settings
naomi/settings/definitions/BAU0.settings
naomi/settings/definitions/BBG0.settings
naomi/settings/definitions/BBN1.settings
naomi/settings/definitions/BDF0.settings
naomi/settings/definitions/BDM0.settings
naomi/settings/definitions/README.md
naomi/settings/definitions/system.settings
settings/README.md
settings/__init__.py
settings/py.typed
settings/settings.py
naomiutils-0.5.4.dist-info/LICENSE
naomiutils-0.5.4.dist-info/METADATA
naomiutils-0.5.4.dist-info/WHEEL
naomiutils-0.5.4.dist-info/top_level.txt
naomiutils-0.5.4.dist-info/RECORD
