Metadata-Version: 2.1
Name: naomiutils
Version: 0.5.4
Summary: Code libraries for working with Naomi ROMs and EEPROMs.
Home-page: https://github.com/DragonMinded/netboot
Author: DragonMinded
Author-email: dragonminded@dragonminded.com
License: Public Domain
Requires-Python: >=3.6
License-File: LICENSE
Requires-Dist: arcadeutils
Requires-Dist: dragoncurses
